Metadata-Version: 2.1
Name: compiler-calc
Version: 0.0.1rc4
Summary: A simple calculator programme
Home-page: https://github.com/tq010or/compiler_calc
Author: Bo HAN
Author-email: bohan.academic@gmail.com
License: UNKNOWN
Platform: UNKNOWN
Classifier: Programming Language :: Python :: 3
Classifier: License :: OSI Approved :: MIT License
Classifier: Operating System :: OS Independent
Requires-Python: >=3.7
